CHANGES.rst
MANIFEST.in
README.rst
setup.py
bin/svn_global.sh
docs/LICENSE.GPL
src/README.txt
src/Products/__init__.py
src/Products.PloneMeeting.egg-info/PKG-INFO
src/Products.PloneMeeting.egg-info/SOURCES.txt
src/Products.PloneMeeting.egg-info/dependency_links.txt
src/Products.PloneMeeting.egg-info/namespace_packages.txt
src/Products.PloneMeeting.egg-info/not-zip-safe
src/Products.PloneMeeting.egg-info/requires.txt
src/Products.PloneMeeting.egg-info/top_level.txt
src/Products/PloneMeeting/EXTEND_GUIDE.txt
src/Products/PloneMeeting/INSTALL.TXT
src/Products/PloneMeeting/LICENSE.GPL
src/Products/PloneMeeting/LICENSE.ZPL
src/Products/PloneMeeting/LICENSE.txt
src/Products/PloneMeeting/Meeting.py
src/Products/PloneMeeting/MeetingCategory.py
src/Products/PloneMeeting/MeetingConfig.py
src/Products/PloneMeeting/MeetingGroup.py
src/Products/PloneMeeting/MeetingItem.py
src/Products/PloneMeeting/MeetingUser.py
src/Products/PloneMeeting/README.txt
src/Products/PloneMeeting/ToolPloneMeeting.py
src/Products/PloneMeeting/__init__.py
src/Products/PloneMeeting/adapters.py
src/Products/PloneMeeting/columns.py
src/Products/PloneMeeting/columns.zcml
src/Products/PloneMeeting/config.py
src/Products/PloneMeeting/configure.zcml
src/Products/PloneMeeting/etags.py
src/Products/PloneMeeting/events.py
src/Products/PloneMeeting/events.zcml
src/Products/PloneMeeting/indexes.py
src/Products/PloneMeeting/interfaces.py
src/Products/PloneMeeting/maintenance.py
src/Products/PloneMeeting/monkey.py
src/Products/PloneMeeting/overrides.zcml
src/Products/PloneMeeting/profiles.zcml
src/Products/PloneMeeting/profiling.zcml
src/Products/PloneMeeting/refresh.txt
src/Products/PloneMeeting/setuphandlers.py
src/Products/PloneMeeting/testing.py
src/Products/PloneMeeting/testing.zcml
src/Products/PloneMeeting/tool.gif
src/Products/PloneMeeting/utils.py
src/Products/PloneMeeting/validators.py
src/Products/PloneMeeting/vocabularies.py
src/Products/PloneMeeting/vocabularies.zcml
src/Products/PloneMeeting/Extensions/__init__.py
src/Products/PloneMeeting/Extensions/imports.py
src/Products/PloneMeeting/behaviors/__init__.py
src/Products/PloneMeeting/behaviors/overrides.py
src/Products/PloneMeeting/browser/__init__.py
src/Products/PloneMeeting/browser/advicechangedelay.py
src/Products/PloneMeeting/browser/adviceinheritance.py
