Metadata-Version: 2.1
Name: Products.PloneMeeting
Version: 4.1.28.15
Summary: Official meetings management
Home-page: https://www.imio.be/nos-applications/ia-delib
Author: Gauthier Bastien
Author-email: gauthier@imio.be
License: GPL
Keywords: plone official meetings management egov communesplone imio plonegov
Platform: UNKNOWN
Classifier: Development Status :: 6 - Mature
Classifier: Environment :: Web Environment
Classifier: Framework :: Plone
Classifier: Framework :: Plone :: 4.3
Classifier: Intended Audience :: Customer Service
Classifier: Intended Audience :: Developers
Classifier: Intended Audience :: End Users/Desktop
Classifier: License :: OSI Approved :: GNU General Public License (GPL)
Classifier: Operating System :: OS Independent
Classifier: Programming Language :: Other Scripting Engines
Classifier: Programming Language :: Python
Classifier: Programming Language :: Python :: 2.7
Classifier: Topic :: Internet :: WWW/HTTP :: Site Management
Classifier: Topic :: Software Development :: Libraries :: Python Modules
Classifier: Topic :: Office/Business
Provides-Extra: templates
Provides-Extra: test
Provides-Extra: amqp
